ImaginEmail-1.1.0.dist-info/DESCRIPTION.rst
ImaginEmail-1.1.0.dist-info/METADATA
ImaginEmail-1.1.0.dist-info/RECORD
ImaginEmail-1.1.0.dist-info/WHEEL
ImaginEmail-1.1.0.dist-info/entry_points.txt
ImaginEmail-1.1.0.dist-info/metadata.json
ImaginEmail-1.1.0.dist-info/top_level.txt
imaginemail/__init__.py
imaginemail/connection.py
imaginemail/imaginemail.py
imaginemail/movie.py
imaginemail/notification.py
imaginemail/scraper.py
imaginemail/tmdb.py
imaginemail/templates/base.html
imaginemail/templates/template.html
