Metadata-Version: 2.0
Name: ImaginEmail
Version: 1.1.0
Summary: ImaginEmail is a program that searches on an specific imaginbank web and notifies a user about new offers and films next to Madrid.
Home-page: https://github.com/daniseijo/imaginemail
Author: Daniel Seijo
Author-email: daniseijo12@gmail.com
License: MIT
Download-URL: https://github.com/daniseijo/imaginemail/archive/1.1.0.tar.gz
Keywords: scraper,imaginbank,email
Platform: UNKNOWN
Requires-Dist: beautifulsoup4 (==4.6.0)
Requires-Dist: requests (==2.18.4)
Requires-Dist: Jinja2 (==2.9.6)
Requires-Dist: Click (==6.7)
